fire_rpc/__init__.py
fire_rpc/__main__.py
fire_rpc-0.1.3.dist-info/LICENSE
fire_rpc-0.1.3.dist-info/METADATA
fire_rpc-0.1.3.dist-info/WHEEL
fire_rpc-0.1.3.dist-info/RECORD
